{
  "template_name": "./config/6.6 BAT.json",
  "pdf_info": {
    "page_size": [
      595.3200073242188,
      841.9199829101562
    ],
    "num_pages": 1
  },
  "fields": [
    {
      "key": "187",
      "placeholderbbox": [
        85.34400177001953,
        762.1409912109375,
        107.64600372314453,
        772.1039428710938
      ],
      "blankbbox": [
        85.5,
        762.0,
        185.5,
        842.0
      ]
    },
    {
      "key": "188",
      "placeholderbbox": [
        286.3699951171875,
        762.1409912109375,
        308.6719665527344,
        772.1039428710938
      ],
      "blankbbox": [
        286.5,
        762.0,
        386.5,
        842.0
      ]
    },
    {
      "key": "189",
      "placeholderbbox": [
        496.4200134277344,
        762.1409912109375,
        518.7220458984375,
        772.1039428710938
      ],
      "blankbbox": [
        496.5,
        762.0,
        595.5,
        842.0
      ]
    },
    {
      "key": "2",
      "placeholderbbox": [
        96.38400268554688,
        79.72099304199219,
        109.5780029296875,
        89.68399047851562
      ],
      "blankbbox": [
        96.5,
        79.5,
        178.0,
        132.5
      ]
    },
    {
      "key": "3",
      "placeholderbbox": [
        249.2899932861328,
        79.72099304199219,
        262.4839782714844,
        89.68399047851562
      ],
      "blankbbox": [
        249.5,
        79.5,
        349.5,
        132.5
      ]
    },
    {
      "key": "4",
      "placeholderbbox": [
        447.70001220703125,
        79.72099304199219,
        460.8940124511719,
        89.68399047851562
      ],
      "blankbbox": [
        447.5,
        79.5,
        547.5,
        132.5
      ]
    },
    {
      "key": "5",
      "placeholderbbox": [
        447.70001220703125,
        108.40098571777344,
        460.8940124511719,
        118.36398315429688
      ],
      "blankbbox": [
        447.5,
        135.5,
        547.5,
        168.0
      ]
    },
    {
      "key": "6",
      "placeholderbbox": [
        96.38400268554688,
        136.9609832763672,
        109.5780029296875,
        146.92398071289062
      ],
      "blankbbox": [
        96.5,
        137.0,
        178.0,
        168.0
      ]
    },
    {
      "key": "7",
      "placeholderbbox": [
        249.2899932861328,
        136.9609832763672,
        262.4839782714844,
        146.92398071289062
      ],
      "blankbbox": [
        249.5,
        137.0,
        349.5,
        168.0
      ]
    },
    {
      "key": "8",
      "placeholderbbox": [
        447.70001220703125,
        136.9609832763672,
        460.8940124511719,
        146.92398071289062
      ],
      "blankbbox": [
        447.5,
        137.0,
        547.5,
        168.0
      ]
    },
    {
      "key": "□Ⅱ",
      "placeholderbbox": [
        279.6499938964844,
        175.28895568847656,
        351.7300109863281,
        184.28895568847656
      ],
      "blankbbox": [
        279.5,
        295.5,
        379.5,
        324.5
      ]
    },
    {
      "key": "□全检",
      "placeholderbbox": [
        456.70001220703125,
        175.28895568847656,
        542.2000122070312,
        184.28895568847656
      ],
      "blankbbox": [
        470.0,
        295.5,
        515.5,
        324.5
      ]
    },
    {
      "key": "□抽检",
      "placeholderbbox": [
        456.70001220703125,
        175.28895568847656,
        542.2000122070312,
        184.28895568847656
      ],
      "blankbbox": [
        470.0,
        295.5,
        515.5,
        324.5
      ]
    },
    {
      "key": "10",
      "placeholderbbox": [
        269.0899963378906,
        213.64097595214844,
        286.8379821777344,
        223.60397338867188
      ],
      "blankbbox": [
        269.0,
        295.5,
        369.0,
        324.5
      ]
    },
    {
      "key": "17",
      "placeholderbbox": [
        395.1099853515625,
        213.64097595214844,
        412.85797119140625,
        223.60397338867188
      ],
      "blankbbox": [
        395.0,
        295.5,
        466.0,
        324.5
      ]
    },
    {
      "key": "24",
      "placeholderbbox": [
        473.1400146484375,
        213.64097595214844,
        490.88800048828125,
        223.60397338867188
      ],
      "blankbbox": [
        519.0,
        296.0,
        573.0,
        324.0
      ]
    },
    {
      "key": "11",
      "placeholderbbox": [
        269.0899963378906,
        245.3509979248047,
        286.48699951171875,
        255.31399536132812
      ],
      "blankbbox": [
        269.0,
        295.5,
        369.0,
        324.5
      ]
    },
    {
      "key": "18",
      "placeholderbbox": [
        395.1099853515625,
        245.3509979248047,
        412.85797119140625,
        255.31399536132812
      ],
      "blankbbox": [
        395.0,
        295.5,
        466.0,
        324.5
      ]
    },
    {
      "key": "25",
      "placeholderbbox": [
        473.1400146484375,
        245.3509979248047,
        490.88800048828125,
        255.31399536132812
      ],
      "blankbbox": [
        519.0,
        296.0,
        573.0,
        324.0
      ]
    },
    {
      "key": "12",
      "placeholderbbox": [
        269.0899963378906,
        265.6309509277344,
        286.8379821777344,
        275.5939636230469
      ],
      "blankbbox": [
        269.0,
        295.5,
        369.0,
        324.5
      ]
    },
    {
      "key": "19",
      "placeholderbbox": [
        395.1099853515625,
        265.6309509277344,
        412.85797119140625,
        275.5939636230469
      ],
      "blankbbox": [
        395.0,
        295.5,
        466.0,
        324.5
      ]
    },
    {
      "key": "26",
      "placeholderbbox": [
        473.1400146484375,
        265.6309509277344,
        490.88800048828125,
        275.5939636230469
      ],
      "blankbbox": [
        519.0,
        296.0,
        573.0,
        324.0
      ]
    },
    {
      "key": "13",
      "placeholderbbox": [
        269.0899963378906,
        297.4309997558594,
        286.8379821777344,
        307.3940124511719
      ],
      "blankbbox": [
        269.0,
        327.5,
        369.0,
        356.0
      ]
    },
    {
      "key": "20",
      "placeholderbbox": [
        395.1099853515625,
        297.4309997558594,
        412.85797119140625,
        307.3940124511719
      ],
      "blankbbox": [
        395.0,
        327.5,
        466.0,
        356.0
      ]
    },
    {
      "key": "27",
      "placeholderbbox": [
        473.1400146484375,
        297.4309997558594,
        490.88800048828125,
        307.3940124511719
      ],
      "blankbbox": [
        473.0,
        400.0,
        568.0,
        417.5
      ]
    },
    {
      "key": "14",
      "placeholderbbox": [
        269.0899963378906,
        329.1109619140625,
        286.8379821777344,
        339.073974609375
      ],
      "blankbbox": [
        269.0,
        329.0,
        369.0,
        356.0
      ]
    },
    {
      "key": "21",
      "placeholderbbox": [
        395.1099853515625,
        329.1109619140625,
        412.85797119140625,
        339.073974609375
      ],
      "blankbbox": [
        395.0,
        329.0,
        466.0,
        356.0
      ]
    },
    {
      "key": "28",
      "placeholderbbox": [
        473.1400146484375,
        329.1109619140625,
        490.88800048828125,
        339.073974609375
      ],
      "blankbbox": [
        473.0,
        400.0,
        568.0,
        417.5
      ]
    },
    {
      "key": "9",
      "placeholderbbox": [
        177.3800048828125,
        362.9509582519531,
        190.5740203857422,
        372.9139709472656
      ],
      "blankbbox": [
        177.5,
        400.0,
        262.0,
        417.5
      ]
    },
    {
      "key": "15",
      "placeholderbbox": [
        269.0899963378906,
        360.7909851074219,
        286.8379821777344,
        370.7539978027344
      ],
      "blankbbox": [
        269.0,
        379.5,
        369.0,
        397.0
      ]
    },
    {
      "key": "22",
      "placeholderbbox": [
        395.1099853515625,
        360.7909851074219,
        412.85797119140625,
        370.7539978027344
      ],
      "blankbbox": [
        395.0,
        400.0,
        495.0,
        417.5
      ]
    },
    {
      "key": "29",
      "placeholderbbox": [
        473.1400146484375,
        360.7909851074219,
        490.88800048828125,
        370.7539978027344
      ],
      "blankbbox": [
        473.0,
        400.0,
        568.0,
        417.5
      ]
    },
    {
      "key": "16",
      "placeholderbbox": [
        269.0899963378906,
        381.19097900390625,
        286.8379821777344,
        391.15399169921875
      ],
      "blankbbox": [
        269.0,
        381.0,
        369.0,
        397.0
      ]
    },
    {
      "key": "23",
      "placeholderbbox": [
        395.1099853515625,
        381.19097900390625,
        412.85797119140625,
        391.15399169921875
      ],
      "blankbbox": [
        395.0,
        400.0,
        495.0,
        417.5
      ]
    },
    {
      "key": "30",
      "placeholderbbox": [
        473.1400146484375,
        381.19097900390625,
        490.88800048828125,
        391.15399169921875
      ],
      "blankbbox": [
        473.0,
        400.0,
        568.0,
        417.5
      ]
    },
    {
      "key": "31",
      "placeholderbbox": [
        31.200000762939453,
        444.3309631347656,
        48.948001861572266,
        454.2939758300781
      ],
      "blankbbox": [
        31.0,
        522.0,
        89.0,
        559.5
      ]
    },
    {
      "key": "32",
      "placeholderbbox": [
        96.38400268554688,
        444.3309631347656,
        114.13200378417969,
        454.2939758300781
      ],
      "blankbbox": [
        135.0,
        522.0,
        173.0,
        559.5
      ]
    },
    {
      "key": "33",
      "placeholderbbox": [
        138.25999450683594,
        444.3309631347656,
        156.0080108642578,
        454.2939758300781
      ],
      "blankbbox": [
        177.0,
        522.0,
        215.0,
        559.5
      ]
    },
    {
      "key": "34",
      "placeholderbbox": [
        180.13999938964844,
        444.3309631347656,
        197.8880157470703,
        454.2939758300781
      ],
      "blankbbox": [
        218.5,
        522.0,
        256.5,
        559.5
      ]
    },
    {
      "key": "35",
      "placeholderbbox": [
        222.0500030517578,
        444.3309631347656,
        239.7980194091797,
        454.2939758300781
      ],
      "blankbbox": [
        260.5,
        522.0,
        298.5,
        559.5
      ]
    },
    {
      "key": "36",
      "placeholderbbox": [
        264.04998779296875,
        444.3309631347656,
        281.7979736328125,
        454.2939758300781
      ],
      "blankbbox": [
        302.5,
        522.0,
        362.5,
        559.5
      ]
    },
    {
      "key": "37",
      "placeholderbbox": [
        305.92999267578125,
        444.3309631347656,
        323.677978515625,
        454.2939758300781
      ],
      "blankbbox": [
        306.0,
        522.0,
        362.5,
        559.5
      ]
    },
    {
      "key": "38",
      "placeholderbbox": [
        369.7900085449219,
        444.3309631347656,
        387.5379943847656,
        454.2939758300781
      ],
      "blankbbox": [
        409.0,
        522.0,
        445.5,
        559.5
      ]
    },
    {
      "key": "39",
      "placeholderbbox": [
        412.2699890136719,
        444.3309631347656,
        430.0179748535156,
        454.2939758300781
      ],
      "blankbbox": [
        449.5,
        522.0,
        486.0,
        559.5
      ]
    },
    {
      "key": "40",
      "placeholderbbox": [
        452.739990234375,
        444.3309631347656,
        470.48797607421875,
        454.2939758300781
      ],
      "blankbbox": [
        490.0,
        522.0,
        527.0,
        559.5
      ]
    },
    {
      "key": "41",
      "placeholderbbox": [
        493.5400085449219,
        444.3309631347656,
        511.2879943847656,
        454.2939758300781
      ],
      "blankbbox": [
        571.0,
        444.5,
        593.5,
        594.5
      ]
    },
    {
      "key": "42",
      "placeholderbbox": [
        534.219970703125,
        444.3309631347656,
        551.968017578125,
        454.2939758300781
      ],
      "blankbbox": [
        571.0,
        444.5,
        595.5,
        594.5
      ]
    },
    {
      "key": "43",
      "placeholderbbox": [
        31.200000762939453,
        464.73095703125,
        48.948001861572266,
        474.6939697265625
      ],
      "blankbbox": [
        31.0,
        522.0,
        89.0,
        559.5
      ]
    },
    {
      "key": "44",
      "placeholderbbox": [
        96.38400268554688,
        464.73095703125,
        114.13200378417969,
        474.6939697265625
      ],
      "blankbbox": [
        135.0,
        522.0,
        173.0,
        559.5
      ]
    },
    {
      "key": "45",
      "placeholderbbox": [
        138.25999450683594,
        464.73095703125,
        156.0080108642578,
        474.6939697265625
      ],
      "blankbbox": [
        177.0,
        522.0,
        215.0,
        559.5
      ]
    },
    {
      "key": "46",
      "placeholderbbox": [
        180.13999938964844,
        464.73095703125,
        197.8880157470703,
        474.6939697265625
      ],
      "blankbbox": [
        218.5,
        522.0,
        256.5,
        559.5
      ]
    },
    {
      "key": "47",
      "placeholderbbox": [
        222.0500030517578,
        464.73095703125,
        239.7980194091797,
        474.6939697265625
      ],
      "blankbbox": [
        260.5,
        522.0,
        298.5,
        559.5
      ]
    },
    {
      "key": "48",
      "placeholderbbox": [
        264.04998779296875,
        464.73095703125,
        281.7979736328125,
        474.6939697265625
      ],
      "blankbbox": [
        302.5,
        522.0,
        362.5,
        559.5
      ]
    },
    {
      "key": "49",
      "placeholderbbox": [
        305.92999267578125,
        464.73095703125,
        323.677978515625,
        474.6939697265625
      ],
      "blankbbox": [
        306.0,
        522.0,
        362.5,
        559.5
      ]
    },
    {
      "key": "50",
      "placeholderbbox": [
        369.7900085449219,
        464.73095703125,
        387.5379943847656,
        474.6939697265625
      ],
      "blankbbox": [
        409.0,
        522.0,
        445.5,
        559.5
      ]
    },
    {
      "key": "51",
      "placeholderbbox": [
        412.2699890136719,
        464.73095703125,
        430.0179748535156,
        474.6939697265625
      ],
      "blankbbox": [
        449.5,
        522.0,
        486.0,
        559.5
      ]
    },
    {
      "key": "52",
      "placeholderbbox": [
        452.739990234375,
        464.73095703125,
        470.48797607421875,
        474.6939697265625
      ],
      "blankbbox": [
        490.0,
        522.0,
        527.0,
        559.5
      ]
    },
    {
      "key": "53",
      "placeholderbbox": [
        493.5400085449219,
        464.73095703125,
        511.2879943847656,
        474.6939697265625
      ],
      "blankbbox": [
        571.0,
        464.5,
        593.5,
        614.5
      ]
    },
    {
      "key": "54",
      "placeholderbbox": [
        534.219970703125,
        464.73095703125,
        551.968017578125,
        474.6939697265625
      ],
      "blankbbox": [
        571.0,
        464.5,
        595.5,
        614.5
      ]
    },
    {
      "key": "55",
      "placeholderbbox": [
        31.200000762939453,
        485.0109558105469,
        48.948001861572266,
        494.9739685058594
      ],
      "blankbbox": [
        31.0,
        522.0,
        89.0,
        559.5
      ]
    },
    {
      "key": "56",
      "placeholderbbox": [
        96.38400268554688,
        485.0109558105469,
        114.13200378417969,
        494.9739685058594
      ],
      "blankbbox": [
        135.0,
        522.0,
        173.0,
        559.5
      ]
    },
    {
      "key": "57",
      "placeholderbbox": [
        138.25999450683594,
        485.0109558105469,
        156.0080108642578,
        494.9739685058594
      ],
      "blankbbox": [
        177.0,
        522.0,
        215.0,
        559.5
      ]
    },
    {
      "key": "58",
      "placeholderbbox": [
        180.13999938964844,
        485.0109558105469,
        197.8880157470703,
        494.9739685058594
      ],
      "blankbbox": [
        218.5,
        522.0,
        256.5,
        559.5
      ]
    },
    {
      "key": "59",
      "placeholderbbox": [
        222.0500030517578,
        485.0109558105469,
        239.7980194091797,
        494.9739685058594
      ],
      "blankbbox": [
        260.5,
        522.0,
        298.5,
        559.5
      ]
    },
    {
      "key": "60",
      "placeholderbbox": [
        264.04998779296875,
        485.0109558105469,
        281.7979736328125,
        494.9739685058594
      ],
      "blankbbox": [
        302.5,
        522.0,
        362.5,
        559.5
      ]
    },
    {
      "key": "61",
      "placeholderbbox": [
        305.92999267578125,
        485.0109558105469,
        323.677978515625,
        494.9739685058594
      ],
      "blankbbox": [
        306.0,
        522.0,
        362.5,
        559.5
      ]
    },
    {
      "key": "62",
      "placeholderbbox": [
        369.7900085449219,
        485.0109558105469,
        387.5379943847656,
        494.9739685058594
      ],
      "blankbbox": [
        409.0,
        522.0,
        445.5,
        559.5
      ]
    },
    {
      "key": "63",
      "placeholderbbox": [
        412.2699890136719,
        485.0109558105469,
        430.0179748535156,
        494.9739685058594
      ],
      "blankbbox": [
        449.5,
        522.0,
        486.0,
        559.5
      ]
    },
    {
      "key": "64",
      "placeholderbbox": [
        452.739990234375,
        485.0109558105469,
        470.48797607421875,
        494.9739685058594
      ],
      "blankbbox": [
        490.0,
        522.0,
        527.0,
        559.5
      ]
    },
    {
      "key": "65",
      "placeholderbbox": [
        493.5400085449219,
        485.0109558105469,
        511.2879943847656,
        494.9739685058594
      ],
      "blankbbox": [
        571.0,
        485.0,
        593.5,
        635.0
      ]
    },
    {
      "key": "66",
      "placeholderbbox": [
        534.219970703125,
        485.0109558105469,
        551.968017578125,
        494.9739685058594
      ],
      "blankbbox": [
        571.0,
        485.0,
        595.5,
        635.0
      ]
    },
    {
      "key": "67",
      "placeholderbbox": [
        31.200000762939453,
        505.4109802246094,
        48.948001861572266,
        515.3739624023438
      ],
      "blankbbox": [
        31.0,
        522.0,
        89.0,
        559.5
      ]
    },
    {
      "key": "68",
      "placeholderbbox": [
        96.38400268554688,
        505.4109802246094,
        114.13200378417969,
        515.3739624023438
      ],
      "blankbbox": [
        135.0,
        522.0,
        173.0,
        559.5
      ]
    },
    {
      "key": "69",
      "placeholderbbox": [
        138.25999450683594,
        505.4109802246094,
        156.0080108642578,
        515.3739624023438
      ],
      "blankbbox": [
        177.0,
        522.0,
        215.0,
        559.5
      ]
    },
    {
      "key": "70",
      "placeholderbbox": [
        180.13999938964844,
        505.4109802246094,
        197.8880157470703,
        515.3739624023438
      ],
      "blankbbox": [
        218.5,
        522.0,
        256.5,
        559.5
      ]
    },
    {
      "key": "71",
      "placeholderbbox": [
        222.0500030517578,
        505.4109802246094,
        239.7980194091797,
        515.3739624023438
      ],
      "blankbbox": [
        260.5,
        522.0,
        298.5,
        559.5
      ]
    },
    {
      "key": "72",
      "placeholderbbox": [
        264.04998779296875,
        505.4109802246094,
        281.7979736328125,
        515.3739624023438
      ],
      "blankbbox": [
        302.5,
        522.0,
        362.5,
        559.5
      ]
    },
    {
      "key": "73",
      "placeholderbbox": [
        305.92999267578125,
        505.4109802246094,
        323.677978515625,
        515.3739624023438
      ],
      "blankbbox": [
        306.0,
        522.0,
        362.5,
        559.5
      ]
    },
    {
      "key": "74",
      "placeholderbbox": [
        369.7900085449219,
        505.4109802246094,
        387.5379943847656,
        515.3739624023438
      ],
      "blankbbox": [
        409.0,
        522.0,
        445.5,
        559.5
      ]
    },
    {
      "key": "75",
      "placeholderbbox": [
        412.2699890136719,
        505.4109802246094,
        430.0179748535156,
        515.3739624023438
      ],
      "blankbbox": [
        449.5,
        522.0,
        486.0,
        559.5
      ]
    },
    {
      "key": "76",
      "placeholderbbox": [
        452.739990234375,
        505.4109802246094,
        470.48797607421875,
        515.3739624023438
      ],
      "blankbbox": [
        490.0,
        522.0,
        527.0,
        559.5
      ]
    },
    {
      "key": "77",
      "placeholderbbox": [
        493.5400085449219,
        505.4109802246094,
        511.2879943847656,
        515.3739624023438
      ],
      "blankbbox": [
        571.0,
        505.5,
        593.5,
        655.5
      ]
    },
    {
      "key": "78",
      "placeholderbbox": [
        534.219970703125,
        505.4109802246094,
        551.968017578125,
        515.3739624023438
      ],
      "blankbbox": [
        571.0,
        505.5,
        595.5,
        655.5
      ]
    },
    {
      "key": "79",
      "placeholderbbox": [
        31.200000762939453,
        525.6909790039062,
        48.948001861572266,
        535.6539306640625
      ],
      "blankbbox": [
        31.0,
        525.5,
        89.0,
        559.5
      ]
    },
    {
      "key": "80",
      "placeholderbbox": [
        96.38400268554688,
        525.6909790039062,
        114.13200378417969,
        535.6539306640625
      ],
      "blankbbox": [
        135.0,
        525.5,
        173.0,
        559.5
      ]
    },
    {
      "key": "81",
      "placeholderbbox": [
        138.25999450683594,
        525.6909790039062,
        156.0080108642578,
        535.6539306640625
      ],
      "blankbbox": [
        177.0,
        525.5,
        215.0,
        559.5
      ]
    },
    {
      "key": "82",
      "placeholderbbox": [
        180.13999938964844,
        525.6909790039062,
        197.8880157470703,
        535.6539306640625
      ],
      "blankbbox": [
        218.5,
        525.5,
        256.5,
        559.5
      ]
    },
    {
      "key": "83",
      "placeholderbbox": [
        222.0500030517578,
        525.6909790039062,
        239.7980194091797,
        535.6539306640625
      ],
      "blankbbox": [
        260.5,
        525.5,
        298.5,
        559.5
      ]
    },
    {
      "key": "84",
      "placeholderbbox": [
        264.04998779296875,
        525.6909790039062,
        281.7979736328125,
        535.6539306640625
      ],
      "blankbbox": [
        302.5,
        525.5,
        362.5,
        559.5
      ]
    },
    {
      "key": "85",
      "placeholderbbox": [
        305.92999267578125,
        525.6909790039062,
        323.677978515625,
        535.6539306640625
      ],
      "blankbbox": [
        306.0,
        525.5,
        362.5,
        559.5
      ]
    },
    {
      "key": "86",
      "placeholderbbox": [
        369.7900085449219,
        525.6909790039062,
        387.5379943847656,
        535.6539306640625
      ],
      "blankbbox": [
        409.0,
        525.5,
        445.5,
        559.5
      ]
    },
    {
      "key": "87",
      "placeholderbbox": [
        412.2699890136719,
        525.6909790039062,
        430.0179748535156,
        535.6539306640625
      ],
      "blankbbox": [
        449.5,
        525.5,
        486.0,
        559.5
      ]
    },
    {
      "key": "88",
      "placeholderbbox": [
        452.739990234375,
        525.6909790039062,
        470.48797607421875,
        535.6539306640625
      ],
      "blankbbox": [
        490.0,
        525.5,
        527.0,
        559.5
      ]
    },
    {
      "key": "89",
      "placeholderbbox": [
        493.5400085449219,
        525.6909790039062,
        511.2879943847656,
        535.6539306640625
      ],
      "blankbbox": [
        571.0,
        525.5,
        593.5,
        675.5
      ]
    },
    {
      "key": "90",
      "placeholderbbox": [
        534.219970703125,
        525.6909790039062,
        551.968017578125,
        535.6539306640625
      ],
      "blankbbox": [
        571.0,
        525.5,
        595.5,
        675.5
      ]
    },
    {
      "key": "91",
      "placeholderbbox": [
        31.200000762939453,
        546.0910034179688,
        48.948001861572266,
        556.053955078125
      ],
      "blankbbox": [
        31.0,
        664.5,
        89.0,
        696.0
      ]
    },
    {
      "key": "92",
      "placeholderbbox": [
        96.38400268554688,
        546.0910034179688,
        114.13200378417969,
        556.053955078125
      ],
      "blankbbox": [
        135.0,
        664.5,
        173.0,
        696.0
      ]
    },
    {
      "key": "93",
      "placeholderbbox": [
        138.25999450683594,
        546.0910034179688,
        156.0080108642578,
        556.053955078125
      ],
      "blankbbox": [
        177.0,
        664.5,
        215.0,
        696.0
      ]
    },
    {
      "key": "94",
      "placeholderbbox": [
        180.13999938964844,
        546.0910034179688,
        197.8880157470703,
        556.053955078125
      ],
      "blankbbox": [
        180.0,
        563.0,
        257.0,
        579.5
      ]
    },
    {
      "key": "95",
      "placeholderbbox": [
        222.0500030517578,
        546.0910034179688,
        239.7980194091797,
        556.053955078125
      ],
      "blankbbox": [
        260.5,
        664.5,
        298.5,
        696.0
      ]
    },
    {
      "key": "96",
      "placeholderbbox": [
        264.04998779296875,
        546.0910034179688,
        281.7979736328125,
        556.053955078125
      ],
      "blankbbox": [
        302.5,
        664.5,
        362.5,
        696.0
      ]
    },
    {
      "key": "97",
      "placeholderbbox": [
        305.92999267578125,
        546.0910034179688,
        323.677978515625,
        556.053955078125
      ],
      "blankbbox": [
        306.0,
        664.5,
        362.5,
        696.0
      ]
    },
    {
      "key": "98",
      "placeholderbbox": [
        369.7900085449219,
        546.0910034179688,
        387.5379943847656,
        556.053955078125
      ],
      "blankbbox": [
        409.0,
        664.5,
        445.5,
        696.0
      ]
    },
    {
      "key": "99",
      "placeholderbbox": [
        412.2699890136719,
        546.0910034179688,
        430.0179748535156,
        556.053955078125
      ],
      "blankbbox": [
        449.5,
        664.5,
        486.0,
        696.0
      ]
    },
    {
      "key": "100",
      "placeholderbbox": [
        452.739990234375,
        546.0910034179688,
        475.0419616699219,
        556.053955078125
      ],
      "blankbbox": [
        490.0,
        664.5,
        527.0,
        696.0
      ]
    },
    {
      "key": "101",
      "placeholderbbox": [
        493.5400085449219,
        546.0910034179688,
        515.8419799804688,
        556.053955078125
      ],
      "blankbbox": [
        571.0,
        546.0,
        593.5,
        696.0
      ]
    },
    {
      "key": "102",
      "placeholderbbox": [
        534.219970703125,
        546.0910034179688,
        556.5220336914062,
        556.053955078125
      ],
      "blankbbox": [
        571.0,
        546.0,
        595.5,
        696.0
      ]
    },
    {
      "key": "103",
      "placeholderbbox": [
        31.200000762939453,
        566.52099609375,
        53.50200271606445,
        576.4839477539062
      ],
      "blankbbox": [
        31.0,
        664.5,
        89.0,
        702.0
      ]
    },
    {
      "key": "104",
      "placeholderbbox": [
        96.38400268554688,
        566.52099609375,
        118.68600463867188,
        576.4839477539062
      ],
      "blankbbox": [
        135.0,
        664.5,
        173.0,
        702.0
      ]
    },
    {
      "key": "105",
      "placeholderbbox": [
        138.25999450683594,
        566.52099609375,
        160.56201171875,
        576.4839477539062
      ],
      "blankbbox": [
        177.0,
        664.5,
        215.0,
        702.0
      ]
    },
    {
      "key": "106",
      "placeholderbbox": [
        180.13999938964844,
        566.52099609375,
        202.4420166015625,
        576.4839477539062
      ],
      "blankbbox": [
        218.5,
        664.5,
        256.5,
        702.0
      ]
    },
    {
      "key": "107",
      "placeholderbbox": [
        222.0500030517578,
        566.52099609375,
        244.35202026367188,
        576.4839477539062
      ],
      "blankbbox": [
        260.5,
        664.5,
        298.5,
        702.0
      ]
    },
    {
      "key": "108",
      "placeholderbbox": [
        264.04998779296875,
        566.52099609375,
        286.3519592285156,
        576.4839477539062
      ],
      "blankbbox": [
        302.5,
        664.5,
        362.5,
        702.0
      ]
    },
    {
      "key": "109",
      "placeholderbbox": [
        305.92999267578125,
        566.52099609375,
        328.2319641113281,
        576.4839477539062
      ],
      "blankbbox": [
        306.0,
        664.5,
        362.5,
        702.0
      ]
    },
    {
      "key": "110",
      "placeholderbbox": [
        369.7900085449219,
        566.52099609375,
        391.7409973144531,
        576.4839477539062
      ],
      "blankbbox": [
        409.0,
        664.5,
        445.5,
        702.0
      ]
    },
    {
      "key": "111",
      "placeholderbbox": [
        412.2699890136719,
        566.52099609375,
        433.8699951171875,
        576.4839477539062
      ],
      "blankbbox": [
        449.5,
        664.5,
        486.0,
        702.0
      ]
    },
    {
      "key": "112",
      "placeholderbbox": [
        452.739990234375,
        566.52099609375,
        474.69097900390625,
        576.4839477539062
      ],
      "blankbbox": [
        490.0,
        664.5,
        527.0,
        702.0
      ]
    },
    {
      "key": "113",
      "placeholderbbox": [
        493.5400085449219,
        566.52099609375,
        515.490966796875,
        576.4839477539062
      ],
      "blankbbox": [
        571.0,
        566.5,
        593.5,
        716.5
      ]
    },
    {
      "key": "114",
      "placeholderbbox": [
        534.219970703125,
        566.52099609375,
        556.1710205078125,
        576.4839477539062
      ],
      "blankbbox": [
        571.0,
        566.5,
        595.5,
        716.5
      ]
    },
    {
      "key": "115",
      "placeholderbbox": [
        31.200000762939453,
        586.8009643554688,
        53.1510009765625,
        596.763916015625
      ],
      "blankbbox": [
        53.0,
        705.0,
        131.0,
        737.0
      ]
    },
    {
      "key": "116",
      "placeholderbbox": [
        96.38400268554688,
        586.8009643554688,
        118.33500671386719,
        596.763916015625
      ],
      "blankbbox": [
        96.5,
        705.0,
        196.5,
        737.0
      ]
    },
    {
      "key": "117",
      "placeholderbbox": [
        138.25999450683594,
        586.8009643554688,
        160.2110137939453,
        596.763916015625
      ],
      "blankbbox": [
        138.5,
        705.0,
        238.5,
        737.0
      ]
    },
    {
      "key": "118",
      "placeholderbbox": [
        180.13999938964844,
        586.8009643554688,
        202.0910186767578,
        596.763916015625
      ],
      "blankbbox": [
        180.0,
        705.0,
        280.0,
        737.0
      ]
    },
    {
      "key": "119",
      "placeholderbbox": [
        222.0500030517578,
        586.8009643554688,
        244.0010223388672,
        596.763916015625
      ],
      "blankbbox": [
        222.0,
        705.0,
        322.0,
        737.0
      ]
    },
    {
      "key": "120",
      "placeholderbbox": [
        264.04998779296875,
        586.8009643554688,
        286.3519592285156,
        596.763916015625
      ],
      "blankbbox": [
        264.0,
        705.0,
        364.0,
        737.0
      ]
    },
    {
      "key": "121",
      "placeholderbbox": [
        305.92999267578125,
        586.8009643554688,
        328.2319641113281,
        596.763916015625
      ],
      "blankbbox": [
        306.0,
        705.0,
        388.0,
        737.0
      ]
    },
    {
      "key": "122",
      "placeholderbbox": [
        369.7900085449219,
        586.8009643554688,
        392.09197998046875,
        596.763916015625
      ],
      "blankbbox": [
        409.0,
        664.5,
        445.5,
        702.0
      ]
    },
    {
      "key": "123",
      "placeholderbbox": [
        412.2699890136719,
        586.8009643554688,
        434.57196044921875,
        596.763916015625
      ],
      "blankbbox": [
        449.5,
        664.5,
        486.0,
        702.0
      ]
    },
    {
      "key": "124",
      "placeholderbbox": [
        452.739990234375,
        586.8009643554688,
        475.0419616699219,
        596.763916015625
      ],
      "blankbbox": [
        490.0,
        664.5,
        527.0,
        702.0
      ]
    },
    {
      "key": "125",
      "placeholderbbox": [
        493.5400085449219,
        586.8009643554688,
        515.8419799804688,
        596.763916015625
      ],
      "blankbbox": [
        571.0,
        587.0,
        593.5,
        737.0
      ]
    },
    {
      "key": "126",
      "placeholderbbox": [
        534.219970703125,
        586.8009643554688,
        556.5220336914062,
        596.763916015625
      ],
      "blankbbox": [
        571.0,
        587.0,
        595.5,
        737.0
      ]
    },
    {
      "key": "127",
      "placeholderbbox": [
        31.200000762939453,
        607.2009887695312,
        53.50200271606445,
        617.1639404296875
      ],
      "blankbbox": [
        53.0,
        705.0,
        131.0,
        749.5
      ]
    },
    {
      "key": "128",
      "placeholderbbox": [
        96.38400268554688,
        607.2009887695312,
        118.68600463867188,
        617.1639404296875
      ],
      "blankbbox": [
        96.5,
        705.0,
        196.5,
        749.5
      ]
    },
    {
      "key": "129",
      "placeholderbbox": [
        138.25999450683594,
        607.2009887695312,
        160.56201171875,
        617.1639404296875
      ],
      "blankbbox": [
        138.5,
        705.0,
        238.5,
        749.5
      ]
    },
    {
      "key": "130",
      "placeholderbbox": [
        180.13999938964844,
        607.2009887695312,
        202.4420166015625,
        617.1639404296875
      ],
      "blankbbox": [
        180.0,
        705.0,
        280.0,
        749.5
      ]
    },
    {
      "key": "131",
      "placeholderbbox": [
        222.0500030517578,
        607.2009887695312,
        244.35202026367188,
        617.1639404296875
      ],
      "blankbbox": [
        222.0,
        705.0,
        322.0,
        749.5
      ]
    },
    {
      "key": "132",
      "placeholderbbox": [
        264.04998779296875,
        607.2009887695312,
        286.3519592285156,
        617.1639404296875
      ],
      "blankbbox": [
        264.0,
        705.0,
        364.0,
        749.5
      ]
    },
    {
      "key": "133",
      "placeholderbbox": [
        305.92999267578125,
        607.2009887695312,
        328.2319641113281,
        617.1639404296875
      ],
      "blankbbox": [
        306.0,
        705.0,
        388.0,
        749.5
      ]
    },
    {
      "key": "134",
      "placeholderbbox": [
        369.7900085449219,
        607.2009887695312,
        392.09197998046875,
        617.1639404296875
      ],
      "blankbbox": [
        409.0,
        664.5,
        445.5,
        702.0
      ]
    },
    {
      "key": "135",
      "placeholderbbox": [
        412.2699890136719,
        607.2009887695312,
        434.57196044921875,
        617.1639404296875
      ],
      "blankbbox": [
        449.5,
        664.5,
        486.0,
        702.0
      ]
    },
    {
      "key": "136",
      "placeholderbbox": [
        452.739990234375,
        607.2009887695312,
        475.0419616699219,
        617.1639404296875
      ],
      "blankbbox": [
        490.0,
        664.5,
        527.0,
        702.0
      ]
    },
    {
      "key": "137",
      "placeholderbbox": [
        493.5400085449219,
        607.2009887695312,
        515.8419799804688,
        617.1639404296875
      ],
      "blankbbox": [
        571.0,
        607.0,
        593.5,
        757.0
      ]
    },
    {
      "key": "138",
      "placeholderbbox": [
        534.219970703125,
        607.2009887695312,
        556.5220336914062,
        617.1639404296875
      ],
      "blankbbox": [
        571.0,
        607.0,
        595.5,
        757.0
      ]
    },
    {
      "key": "139",
      "placeholderbbox": [
        31.200000762939453,
        627.4810180664062,
        53.50200271606445,
        637.4439697265625
      ],
      "blankbbox": [
        53.0,
        705.0,
        131.0,
        749.5
      ]
    },
    {
      "key": "140",
      "placeholderbbox": [
        96.38400268554688,
        627.4810180664062,
        118.68600463867188,
        637.4439697265625
      ],
      "blankbbox": [
        96.5,
        705.0,
        196.5,
        749.5
      ]
    },
    {
      "key": "141",
      "placeholderbbox": [
        138.25999450683594,
        627.4810180664062,
        160.56201171875,
        637.4439697265625
      ],
      "blankbbox": [
        138.5,
        705.0,
        238.5,
        749.5
      ]
    },
    {
      "key": "142",
      "placeholderbbox": [
        180.13999938964844,
        627.4810180664062,
        202.4420166015625,
        637.4439697265625
      ],
      "blankbbox": [
        180.0,
        705.0,
        280.0,
        749.5
      ]
    },
    {
      "key": "143",
      "placeholderbbox": [
        222.0500030517578,
        627.4810180664062,
        244.35202026367188,
        637.4439697265625
      ],
      "blankbbox": [
        222.0,
        705.0,
        322.0,
        749.5
      ]
    },
    {
      "key": "144",
      "placeholderbbox": [
        264.04998779296875,
        627.4810180664062,
        286.3519592285156,
        637.4439697265625
      ],
      "blankbbox": [
        264.0,
        705.0,
        364.0,
        749.5
      ]
    },
    {
      "key": "145",
      "placeholderbbox": [
        305.92999267578125,
        627.4810180664062,
        328.2319641113281,
        637.4439697265625
      ],
      "blankbbox": [
        306.0,
        705.0,
        388.0,
        749.5
      ]
    },
    {
      "key": "146",
      "placeholderbbox": [
        369.7900085449219,
        627.4810180664062,
        392.09197998046875,
        637.4439697265625
      ],
      "blankbbox": [
        370.0,
        752.5,
        470.0,
        777.5
      ]
    },
    {
      "key": "147",
      "placeholderbbox": [
        412.2699890136719,
        627.4810180664062,
        434.57196044921875,
        637.4439697265625
      ],
      "blankbbox": [
        412.5,
        752.5,
        470.0,
        777.5
      ]
    },
    {
      "key": "148",
      "placeholderbbox": [
        452.739990234375,
        627.4810180664062,
        475.0419616699219,
        637.4439697265625
      ],
      "blankbbox": [
        491.0,
        752.5,
        552.5,
        777.5
      ]
    },
    {
      "key": "149",
      "placeholderbbox": [
        493.5400085449219,
        627.4810180664062,
        515.8419799804688,
        637.4439697265625
      ],
      "blankbbox": [
        571.0,
        627.5,
        593.5,
        777.5
      ]
    },
    {
      "key": "150",
      "placeholderbbox": [
        534.219970703125,
        627.4810180664062,
        556.5399780273438,
        637.4439697265625
      ],
      "blankbbox": [
        571.0,
        627.5,
        595.5,
        777.5
      ]
    },
    {
      "key": "151",
      "placeholderbbox": [
        31.200000762939453,
        647.8809814453125,
        53.50200271606445,
        657.8439331054688
      ],
      "blankbbox": [
        53.0,
        705.0,
        131.0,
        749.5
      ]
    },
    {
      "key": "152",
      "placeholderbbox": [
        96.38400268554688,
        647.8809814453125,
        118.68600463867188,
        657.8439331054688
      ],
      "blankbbox": [
        96.5,
        752.5,
        196.5,
        798.0
      ]
    },
    {
      "key": "153",
      "placeholderbbox": [
        138.25999450683594,
        647.8809814453125,
        160.56201171875,
        657.8439331054688
      ],
      "blankbbox": [
        138.5,
        752.5,
        238.5,
        798.0
      ]
    },
    {
      "key": "154",
      "placeholderbbox": [
        180.13999938964844,
        647.8809814453125,
        202.4420166015625,
        657.8439331054688
      ],
      "blankbbox": [
        180.0,
        705.0,
        280.0,
        749.5
      ]
    },
    {
      "key": "155",
      "placeholderbbox": [
        222.0500030517578,
        647.8809814453125,
        244.35202026367188,
        657.8439331054688
      ],
      "blankbbox": [
        222.0,
        705.0,
        322.0,
        749.5
      ]
    },
    {
      "key": "156",
      "placeholderbbox": [
        264.04998779296875,
        647.8809814453125,
        286.3519592285156,
        657.8439331054688
      ],
      "blankbbox": [
        264.0,
        705.0,
        364.0,
        749.5
      ]
    },
    {
      "key": "157",
      "placeholderbbox": [
        305.92999267578125,
        647.8809814453125,
        328.2319641113281,
        657.8439331054688
      ],
      "blankbbox": [
        306.0,
        752.5,
        406.0,
        798.0
      ]
    },
    {
      "key": "158",
      "placeholderbbox": [
        369.7900085449219,
        647.8809814453125,
        392.09197998046875,
        657.8439331054688
      ],
      "blankbbox": [
        370.0,
        752.5,
        470.0,
        798.0
      ]
    },
    {
      "key": "159",
      "placeholderbbox": [
        412.2699890136719,
        647.8809814453125,
        434.57196044921875,
        657.8439331054688
      ],
      "blankbbox": [
        412.5,
        752.5,
        470.0,
        798.0
      ]
    },
    {
      "key": "160",
      "placeholderbbox": [
        452.739990234375,
        647.8809814453125,
        475.0419616699219,
        657.8439331054688
      ],
      "blankbbox": [
        491.0,
        752.5,
        552.5,
        798.0
      ]
    },
    {
      "key": "161",
      "placeholderbbox": [
        493.5400085449219,
        647.8809814453125,
        515.8419799804688,
        657.8439331054688
      ],
      "blankbbox": [
        493.5,
        752.5,
        593.5,
        798.0
      ]
    },
    {
      "key": "162",
      "placeholderbbox": [
        534.219970703125,
        647.8809814453125,
        556.5220336914062,
        657.8439331054688
      ],
      "blankbbox": [
        571.0,
        648.0,
        595.5,
        798.0
      ]
    },
    {
      "key": "163",
      "placeholderbbox": [
        31.200000762939453,
        668.1610107421875,
        53.50200271606445,
        678.1239624023438
      ],
      "blankbbox": [
        31.0,
        772.0,
        131.0,
        818.0
      ]
    },
    {
      "key": "164",
      "placeholderbbox": [
        96.38400268554688,
        668.1610107421875,
        118.68600463867188,
        678.1239624023438
      ],
      "blankbbox": [
        96.5,
        752.5,
        196.5,
        818.0
      ]
    },
    {
      "key": "165",
      "placeholderbbox": [
        138.25999450683594,
        668.1610107421875,
        160.56201171875,
        678.1239624023438
      ],
      "blankbbox": [
        138.5,
        752.5,
        238.5,
        818.0
      ]
    },
    {
      "key": "166",
      "placeholderbbox": [
        180.13999938964844,
        668.1610107421875,
        202.4420166015625,
        678.1239624023438
      ],
      "blankbbox": [
        180.0,
        752.5,
        259.0,
        818.0
      ]
    },
    {
      "key": "167",
      "placeholderbbox": [
        222.0500030517578,
        668.1610107421875,
        244.35202026367188,
        678.1239624023438
      ],
      "blankbbox": [
        222.0,
        772.0,
        322.0,
        818.0
      ]
    },
    {
      "key": "168",
      "placeholderbbox": [
        264.04998779296875,
        668.1610107421875,
        286.3519592285156,
        678.1239624023438
      ],
      "blankbbox": [
        281.0,
        752.5,
        364.0,
        818.0
      ]
    },
    {
      "key": "169",
      "placeholderbbox": [
        305.92999267578125,
        668.1610107421875,
        328.2319641113281,
        678.1239624023438
      ],
      "blankbbox": [
        306.0,
        752.5,
        406.0,
        818.0
      ]
    },
    {
      "key": "170",
      "placeholderbbox": [
        369.7900085449219,
        668.1610107421875,
        392.09197998046875,
        678.1239624023438
      ],
      "blankbbox": [
        370.0,
        752.5,
        470.0,
        818.0
      ]
    },
    {
      "key": "171",
      "placeholderbbox": [
        412.2699890136719,
        668.1610107421875,
        434.57196044921875,
        678.1239624023438
      ],
      "blankbbox": [
        412.5,
        772.0,
        512.5,
        818.0
      ]
    },
    {
      "key": "172",
      "placeholderbbox": [
        452.739990234375,
        668.1610107421875,
        475.0419616699219,
        678.1239624023438
      ],
      "blankbbox": [
        452.5,
        772.0,
        552.5,
        818.0
      ]
    },
    {
      "key": "173",
      "placeholderbbox": [
        493.5400085449219,
        668.1610107421875,
        515.8419799804688,
        678.1239624023438
      ],
      "blankbbox": [
        493.5,
        752.5,
        593.5,
        818.0
      ]
    },
    {
      "key": "174",
      "placeholderbbox": [
        534.219970703125,
        668.1610107421875,
        556.5220336914062,
        678.1239624023438
      ],
      "blankbbox": [
        534.0,
        752.5,
        595.5,
        818.0
      ]
    },
    {
      "key": "175",
      "placeholderbbox": [
        31.200000762939453,
        688.5609741210938,
        53.50200271606445,
        698.52392578125
      ],
      "blankbbox": [
        31.0,
        772.0,
        131.0,
        838.5
      ]
    },
    {
      "key": "176",
      "placeholderbbox": [
        96.38400268554688,
        688.5609741210938,
        118.68600463867188,
        698.52392578125
      ],
      "blankbbox": [
        96.5,
        752.5,
        196.5,
        838.5
      ]
    },
    {
      "key": "177",
      "placeholderbbox": [
        138.25999450683594,
        688.5609741210938,
        160.56201171875,
        698.52392578125
      ],
      "blankbbox": [
        138.5,
        752.5,
        238.5,
        838.5
      ]
    },
    {
      "key": "178",
      "placeholderbbox": [
        180.13999938964844,
        688.5609741210938,
        202.4420166015625,
        698.52392578125
      ],
      "blankbbox": [
        180.0,
        752.5,
        259.0,
        838.5
      ]
    },
    {
      "key": "179",
      "placeholderbbox": [
        222.0500030517578,
        688.5609741210938,
        244.35202026367188,
        698.52392578125
      ],
      "blankbbox": [
        222.0,
        772.0,
        322.0,
        838.5
      ]
    },
    {
      "key": "180",
      "placeholderbbox": [
        264.04998779296875,
        688.5609741210938,
        286.3519592285156,
        698.52392578125
      ],
      "blankbbox": [
        281.0,
        752.5,
        364.0,
        838.5
      ]
    },
    {
      "key": "181",
      "placeholderbbox": [
        305.92999267578125,
        688.5609741210938,
        328.2319641113281,
        698.52392578125
      ],
      "blankbbox": [
        306.0,
        752.5,
        406.0,
        838.5
      ]
    },
    {
      "key": "182",
      "placeholderbbox": [
        369.7900085449219,
        688.5609741210938,
        392.09197998046875,
        698.52392578125
      ],
      "blankbbox": [
        370.0,
        752.5,
        470.0,
        838.5
      ]
    },
    {
      "key": "183",
      "placeholderbbox": [
        412.2699890136719,
        688.5609741210938,
        434.57196044921875,
        698.52392578125
      ],
      "blankbbox": [
        412.5,
        772.0,
        512.5,
        838.5
      ]
    },
    {
      "key": "184",
      "placeholderbbox": [
        452.739990234375,
        688.5609741210938,
        475.0419616699219,
        698.52392578125
      ],
      "blankbbox": [
        452.5,
        772.0,
        552.5,
        838.5
      ]
    },
    {
      "key": "185",
      "placeholderbbox": [
        493.5400085449219,
        688.5609741210938,
        515.8419799804688,
        698.52392578125
      ],
      "blankbbox": [
        493.5,
        752.5,
        593.5,
        838.5
      ]
    },
    {
      "key": "186",
      "placeholderbbox": [
        534.219970703125,
        688.5609741210938,
        556.5220336914062,
        698.52392578125
      ],
      "blankbbox": [
        534.0,
        752.5,
        595.5,
        838.5
      ]
    },
    {
      "key": "□合格",
      "placeholderbbox": [
        484.5400085449219,
        708.1689453125,
        516.0400390625,
        717.1689453125
      ],
      "blankbbox": [
        491.0,
        752.5,
        584.5,
        842.0
      ]
    },
    {
      "key": "1",
      "placeholderbbox": [
        70.58399963378906,
        61.58097457885742,
        83.77799987792969,
        71.54397583007812
      ],
      "blankbbox": [
        93.0,
        78.0,
        170.5,
        132.5
      ]
    }
  ]
}