{
  "template_name": "./config/6.12 FUSE.json",
  "pdf_info": {
    "page_size": [
      595.3200073242188,
      841.9199829101562
    ],
    "num_pages": 1
  },
  "fields": [
    {
      "key": "24",
      "placeholderbbox": [
        85.34400177001953,
        727.6289672851562,
        103.38899993896484,
        736.6289672851562
      ],
      "blankbbox": [
        85.5,
        727.5,
        185.5,
        842.0
      ]
    },
    {
      "key": "25",
      "placeholderbbox": [
        265.3699951171875,
        727.6289672851562,
        283.41497802734375,
        736.6289672851562
      ],
      "blankbbox": [
        265.5,
        727.5,
        365.5,
        842.0
      ]
    },
    {
      "key": "26",
      "placeholderbbox": [
        433.3900146484375,
        727.6289672851562,
        451.43499755859375,
        736.6289672851562
      ],
      "blankbbox": [
        433.5,
        727.5,
        533.5,
        842.0
      ]
    },
    {
      "key": "2",
      "placeholderbbox": [
        93.26399993896484,
        79.72099304199219,
        106.45800018310547,
        89.68399047851562
      ],
      "blankbbox": [
        93.5,
        79.5,
        186.0,
        132.5
      ]
    },
    {
      "key": "3",
      "placeholderbbox": [
        256.3699951171875,
        79.72099304199219,
        269.5639953613281,
        89.68399047851562
      ],
      "blankbbox": [
        256.5,
        79.5,
        356.5,
        132.5
      ]
    },
    {
      "key": "4",
      "placeholderbbox": [
        454.8999938964844,
        79.72099304199219,
        468.093994140625,
        89.68399047851562
      ],
      "blankbbox": [
        455.0,
        79.5,
        555.0,
        104.0
      ]
    },
    {
      "key": "5",
      "placeholderbbox": [
        454.8999938964844,
        108.40098571777344,
        468.093994140625,
        118.36398315429688
      ],
      "blankbbox": [
        455.0,
        108.5,
        555.0,
        132.5
      ]
    },
    {
      "key": "6",
      "placeholderbbox": [
        93.26399993896484,
        136.9609832763672,
        106.45800018310547,
        146.92398071289062
      ],
      "blankbbox": [
        93.5,
        137.0,
        186.0,
        164.0
      ]
    },
    {
      "key": "7",
      "placeholderbbox": [
        256.3699951171875,
        136.9609832763672,
        269.5639953613281,
        146.92398071289062
      ],
      "blankbbox": [
        256.5,
        137.0,
        356.5,
        164.0
      ]
    },
    {
      "key": "8",
      "placeholderbbox": [
        454.8999938964844,
        136.9609832763672,
        468.093994140625,
        146.92398071289062
      ],
      "blankbbox": [
        455.0,
        137.0,
        555.0,
        164.0
      ]
    },
    {
      "key": "□Ⅱ",
      "placeholderbbox": [
        286.7300109863281,
        173.1289825439453,
        358.80999755859375,
        182.1289825439453
      ],
      "blankbbox": [
        286.5,
        173.0,
        287.0,
        188.5
      ]
    },
    {
      "key": "□全检",
      "placeholderbbox": [
        463.8999938964844,
        173.1289825439453,
        549.4000244140625,
        182.1289825439453
      ],
      "blankbbox": [
        464.0,
        173.0,
        473.5,
        173.5
      ]
    },
    {
      "key": "□抽检",
      "placeholderbbox": [
        463.8999938964844,
        173.1289825439453,
        549.4000244140625,
        182.1289825439453
      ],
      "blankbbox": [
        464.0,
        173.0,
        473.5,
        173.5
      ]
    },
    {
      "key": "9",
      "placeholderbbox": [
        270.5299987792969,
        212.0809783935547,
        283.7239990234375,
        222.04397583007812
      ],
      "blankbbox": [
        270.5,
        212.0,
        370.5,
        239.0
      ]
    },
    {
      "key": "14",
      "placeholderbbox": [
        395.1099853515625,
        212.0809783935547,
        412.85797119140625,
        222.04397583007812
      ],
      "blankbbox": [
        395.0,
        212.0,
        466.5,
        239.0
      ]
    },
    {
      "key": "19",
      "placeholderbbox": [
        473.1400146484375,
        212.0809783935547,
        490.88800048828125,
        222.04397583007812
      ],
      "blankbbox": [
        473.0,
        212.0,
        516.0,
        239.0
      ]
    },
    {
      "key": "10",
      "placeholderbbox": [
        270.5299987792969,
        243.79100036621094,
        288.2779846191406,
        253.75399780273438
      ],
      "blankbbox": [
        270.5,
        244.0,
        370.5,
        286.5
      ]
    },
    {
      "key": "15",
      "placeholderbbox": [
        395.1099853515625,
        243.79100036621094,
        412.85797119140625,
        253.75399780273438
      ],
      "blankbbox": [
        395.0,
        244.0,
        466.5,
        286.5
      ]
    },
    {
      "key": "20",
      "placeholderbbox": [
        473.1400146484375,
        243.79100036621094,
        490.88800048828125,
        253.75399780273438
      ],
      "blankbbox": [
        473.0,
        244.0,
        516.0,
        286.5
      ]
    },
    {
      "key": "11",
      "placeholderbbox": [
        270.5299987792969,
        291.1909484863281,
        287.927001953125,
        301.1539611816406
      ],
      "blankbbox": [
        270.5,
        291.0,
        370.5,
        318.0
      ]
    },
    {
      "key": "16",
      "placeholderbbox": [
        395.1099853515625,
        291.1909484863281,
        412.85797119140625,
        301.1539611816406
      ],
      "blankbbox": [
        395.0,
        291.0,
        466.5,
        318.0
      ]
    },
    {
      "key": "21",
      "placeholderbbox": [
        473.1400146484375,
        291.1909484863281,
        490.88800048828125,
        301.1539611816406
      ],
      "blankbbox": [
        473.0,
        291.0,
        516.0,
        318.0
      ]
    },
    {
      "key": "12",
      "placeholderbbox": [
        270.5299987792969,
        322.8709716796875,
        288.2779846191406,
        332.833984375
      ],
      "blankbbox": [
        270.5,
        323.0,
        370.5,
        350.0
      ]
    },
    {
      "key": "17",
      "placeholderbbox": [
        395.1099853515625,
        322.8709716796875,
        412.85797119140625,
        332.833984375
      ],
      "blankbbox": [
        395.0,
        323.0,
        466.5,
        350.0
      ]
    },
    {
      "key": "22",
      "placeholderbbox": [
        473.1400146484375,
        322.8709716796875,
        490.88800048828125,
        332.833984375
      ],
      "blankbbox": [
        473.0,
        323.0,
        516.0,
        350.0
      ]
    },
    {
      "key": "13",
      "placeholderbbox": [
        270.5299987792969,
        354.55096435546875,
        288.2779846191406,
        364.51397705078125
      ],
      "blankbbox": [
        270.5,
        354.5,
        370.5,
        381.5
      ]
    },
    {
      "key": "18",
      "placeholderbbox": [
        395.1099853515625,
        354.55096435546875,
        412.85797119140625,
        364.51397705078125
      ],
      "blankbbox": [
        395.0,
        354.5,
        466.5,
        381.5
      ]
    },
    {
      "key": "23",
      "placeholderbbox": [
        473.1400146484375,
        354.55096435546875,
        490.88800048828125,
        364.51397705078125
      ],
      "blankbbox": [
        473.0,
        354.5,
        516.0,
        381.5
      ]
    },
    {
      "key": "□合格",
      "placeholderbbox": [
        454.8999938964844,
        648.1689453125,
        486.3999938964844,
        657.1689453125
      ],
      "blankbbox": [
        455.0,
        648.0,
        466.5,
        648.5
      ]
    },
    {
      "key": "1",
      "placeholderbbox": [
        70.58399963378906,
        61.58097457885742,
        83.77799987792969,
        71.54397583007812
      ],
      "blankbbox": [
        70.5,
        61.5,
        170.5,
        75.0
      ]
    }
  ]
}