{
  "template_name": "./config/6.64 ACDC.json",
  "pdf_info": {
    "page_size": [
      595.3200073242188,
      841.9199829101562
    ],
    "num_pages": 1
  },
  "fields": [
    {
      "key": "24",
      "placeholderbbox": [
        85.34400177001953,
        749.948974609375,
        103.38899993896484,
        758.948974609375
      ],
      "blankbbox": [
        171,
        1500,
        231,
        1680
      ]
    },
    {
      "key": "25",
      "placeholderbbox": [
        286.3699951171875,
        749.948974609375,
        304.41497802734375,
        758.948974609375
      ],
      "blankbbox": [
        573,
        1500,
        633,
        1680
      ]
    },
    {
      "key": "26",
      "placeholderbbox": [
        475.4200134277344,
        749.948974609375,
        493.4649963378906,
        758.948974609375
      ],
      "blankbbox": [
        951,
        1500,
        1011,
        1680
      ]
    },
    {
      "key": "2",
      "placeholderbbox": [
        96.38400268554688,
        79.72099304199219,
        109.5780029296875,
        89.68399047851562
      ],
      "blankbbox": [
        193,
        159,
        253,
        277
      ]
    },
    {
      "key": "3",
      "placeholderbbox": [
        256.3699951171875,
        79.72099304199219,
        269.5639953613281,
        89.68399047851562
      ],
      "blankbbox": [
        513,
        159,
        573,
        277
      ]
    },
    {
      "key": "4",
      "placeholderbbox": [
        483.1000061035156,
        79.72099304199219,
        496.29400634765625,
        89.68399047851562
      ],
      "blankbbox": [
        966,
        159,
        1026,
        277
      ]
    },
    {
      "key": "5",
      "placeholderbbox": [
        483.1000061035156,
        111.40098571777344,
        496.29400634765625,
        121.36398315429688
      ],
      "blankbbox": [
        982,
        283,
        1026,
        389
      ]
    },
    {
      "key": "6",
      "placeholderbbox": [
        96.38400268554688,
        143.2009735107422,
        109.5780029296875,
        153.16397094726562
      ],
      "blankbbox": [
        193,
        286,
        253,
        359
      ]
    },
    {
      "key": "7",
      "placeholderbbox": [
        256.3699951171875,
        143.2009735107422,
        269.5639953613281,
        153.16397094726562
      ],
      "blankbbox": [
        513,
        286,
        573,
        358
      ]
    },
    {
      "key": "8",
      "placeholderbbox": [
        483.1000061035156,
        143.2009735107422,
        496.29400634765625,
        153.16397094726562
      ],
      "blankbbox": [
        982,
        286,
        1026,
        389
      ]
    },
    {
      "key": "□Ⅱ",
      "placeholderbbox": [
        260.92999267578125,
        179.2489776611328,
        333.010009765625,
        188.2489776611328
      ],
      "blankbbox": [
        522,
        444,
        582,
        500
      ]
    },
    {
      "key": "□全检",
      "placeholderbbox": [
        463.8999938964844,
        179.2489776611328,
        549.4000244140625,
        188.2489776611328
      ],
      "blankbbox": [
        940,
        443,
        988,
        501
      ]
    },
    {
      "key": "□抽检",
      "placeholderbbox": [
        463.8999938964844,
        179.2489776611328,
        549.4000244140625,
        188.2489776611328
      ],
      "blankbbox": [
        940,
        443,
        988,
        501
      ]
    },
    {
      "key": "9",
      "placeholderbbox": [
        269.0899963378906,
        223.3610076904297,
        282.28399658203125,
        233.32400512695312
      ],
      "blankbbox": [
        538,
        507,
        598,
        627
      ]
    },
    {
      "key": "14",
      "placeholderbbox": [
        395.1099853515625,
        223.3610076904297,
        412.85797119140625,
        233.32400512695312
      ],
      "blankbbox": [
        790,
        507,
        850,
        627
      ]
    },
    {
      "key": "19",
      "placeholderbbox": [
        473.1400146484375,
        223.3610076904297,
        490.88800048828125,
        233.32400512695312
      ],
      "blankbbox": [
        946,
        507,
        1006,
        627
      ]
    },
    {
      "key": "10",
      "placeholderbbox": [
        269.0899963378906,
        255.0709686279297,
        286.8379821777344,
        265.0339660644531
      ],
      "blankbbox": [
        538,
        510,
        598,
        690
      ]
    },
    {
      "key": "15",
      "placeholderbbox": [
        395.1099853515625,
        255.0709686279297,
        412.85797119140625,
        265.0339660644531
      ],
      "blankbbox": [
        790,
        510,
        850,
        690
      ]
    },
    {
      "key": "20",
      "placeholderbbox": [
        473.1400146484375,
        255.0709686279297,
        490.88800048828125,
        265.0339660644531
      ],
      "blankbbox": [
        946,
        510,
        1006,
        690
      ]
    },
    {
      "key": "11",
      "placeholderbbox": [
        269.0899963378906,
        411.57098388671875,
        286.48699951171875,
        421.53399658203125
      ],
      "blankbbox": [
        538,
        914,
        598,
        1003
      ]
    },
    {
      "key": "16",
      "placeholderbbox": [
        395.1099853515625,
        411.57098388671875,
        412.85797119140625,
        421.53399658203125
      ],
      "blankbbox": [
        790,
        914,
        850,
        1003
      ]
    },
    {
      "key": "21",
      "placeholderbbox": [
        473.1400146484375,
        411.57098388671875,
        490.88800048828125,
        421.53399658203125
      ],
      "blankbbox": [
        946,
        914,
        1006,
        1003
      ]
    },
    {
      "key": "12",
      "placeholderbbox": [
        269.0899963378906,
        458.8509826660156,
        286.8379821777344,
        468.8139953613281
      ],
      "blankbbox": [
        538,
        1009,
        598,
        1098
      ]
    },
    {
      "key": "17",
      "placeholderbbox": [
        395.1099853515625,
        458.8509826660156,
        412.85797119140625,
        468.8139953613281
      ],
      "blankbbox": [
        790,
        1009,
        850,
        1098
      ]
    },
    {
      "key": "22",
      "placeholderbbox": [
        473.1400146484375,
        458.8509826660156,
        490.88800048828125,
        468.8139953613281
      ],
      "blankbbox": [
        946,
        1009,
        1006,
        1098
      ]
    },
    {
      "key": "13",
      "placeholderbbox": [
        269.0899963378906,
        506.2510070800781,
        286.8379821777344,
        516.2139892578125
      ],
      "blankbbox": [
        538,
        1013,
        598,
        1098
      ]
    },
    {
      "key": "18",
      "placeholderbbox": [
        395.1099853515625,
        506.2510070800781,
        412.85797119140625,
        516.2139892578125
      ],
      "blankbbox": [
        790,
        1013,
        850,
        1098
      ]
    },
    {
      "key": "23",
      "placeholderbbox": [
        473.1400146484375,
        506.2510070800781,
        490.88800048828125,
        516.2139892578125
      ],
      "blankbbox": [
        946,
        1013,
        1006,
        1098
      ]
    },
    {
      "key": "□合格",
      "placeholderbbox": [
        484.5400085449219,
        695.68896484375,
        516.0400390625,
        704.68896484375
      ],
      "blankbbox": [
        969,
        1480,
        1029,
        1571
      ]
    },
    {
      "key": "1",
      "placeholderbbox": [
        70.58399963378906,
        61.58097457885742,
        83.77799987792969,
        71.54397583007812
      ],
      "blankbbox": [
        153,
        157,
        179,
        276
      ]
    }
  ]
}